netaccess/__init__.py
netaccess/netaccess.py
netaccess-1.0.2.dist-info/LICENSE
netaccess-1.0.2.dist-info/METADATA
netaccess-1.0.2.dist-info/WHEEL
netaccess-1.0.2.dist-info/entry_points.txt
netaccess-1.0.2.dist-info/top_level.txt
netaccess-1.0.2.dist-info/RECORD
