Metadata-Version: 2.1
Name: netaccess
Version: 1.0.2
Summary: CLI for IIT Madras netaccess
Home-page: https://github.com/haranrk/IITM-Netaccess-Approval
Author: Haran Rajkumar
Author-email: haranrajkumar97@gmail.com
License: UNKNOWN
Platform: UNKNOWN
Classifier: Programming Language :: Python :: 3.5
Classifier: License :: OSI Approved :: MIT License
Classifier: Operating System :: OS Independent
Requires-Dist: mechanize
